<?xml version="1.0" encoding="UTF-8"?><record_update sys_domain="global" table="sys_ui_policy">
    <sys_ui_policy action="DELETE">
        <active>true</active>
        <conditions table="x_1800027_leve_sys_leave_request">approverISEMPTY^EQ<item endquery="false" field="approver" goto="false" newquery="false" operator="ISEMPTY" or="false" value=""/>
            <item endquery="true" field="" goto="false" newquery="false" operator="=" or="false" value=""/>
        </conditions>
        <description/>
        <global>true</global>
        <inherit>false</inherit>
        <isolate_script>true</isolate_script>
        <model_id/>
        <model_table/>
        <on_load>true</on_load>
        <order>100</order>
        <reverse_if_false>true</reverse_if_false>
        <run_scripts>false</run_scripts>
        <script_false><![CDATA[function onCondition() {

}]]></script_false>
        <script_true><![CDATA[function onCondition() {

}]]></script_true>
        <set_values/>
        <short_description>auto populate manager</short_description>
        <sys_class_name>sys_ui_policy</sys_class_name>
        <sys_created_by>admin</sys_created_by>
        <sys_created_on>2025-07-18 12:04:59</sys_created_on>
        <sys_domain>global</sys_domain>
        <sys_domain_path>/</sys_domain_path>
        <sys_id>1dd2aaf1c33a6210a7f1b813e4013118</sys_id>
        <sys_mod_count>2</sys_mod_count>
        <sys_name>auto populate manager</sys_name>
        <sys_overrides/>
        <sys_package display_value="Leave Management System" source="x_1800027_leve_sys">9b184465c3beaa10a7f1b813e4013155</sys_package>
        <sys_policy/>
        <sys_scope display_value="Leave Management System">9b184465c3beaa10a7f1b813e4013155</sys_scope>
        <sys_update_name>sys_ui_policy_1dd2aaf1c33a6210a7f1b813e4013118</sys_update_name>
        <sys_updated_by>admin</sys_updated_by>
        <sys_updated_on>2025-07-18 12:10:59</sys_updated_on>
        <table>x_1800027_leve_sys_leave_request</table>
        <ui_type>10</ui_type>
        <view/>
    </sys_ui_policy>
    <sys_update_version action="INSERT_OR_UPDATE">
        <action>DELETE</action>
        <application display_value="Leave Management System">9b184465c3beaa10a7f1b813e4013155</application>
        <file_path/>
        <instance_id>77ceb617fb135ad452b0f3585eefdcac</instance_id>
        <instance_name>dev293426</instance_name>
        <name>sys_ui_policy_1dd2aaf1c33a6210a7f1b813e4013118</name>
        <payload>&lt;?xml version="1.0" encoding="UTF-8"?&gt;&lt;record_update sys_domain="global" table="sys_ui_policy"&gt;&lt;sys_ui_policy action="INSERT_OR_UPDATE"&gt;&lt;active&gt;true&lt;/active&gt;&lt;conditions table="x_1800027_leve_sys_leave_request"&gt;approverISEMPTY^EQ&lt;item endquery="false" field="approver" goto="false" newquery="false" operator="ISEMPTY" or="false" value=""/&gt;&lt;item endquery="true" field="" goto="false" newquery="false" operator="=" or="false" value=""/&gt;&lt;/conditions&gt;&lt;description/&gt;&lt;global&gt;true&lt;/global&gt;&lt;inherit&gt;false&lt;/inherit&gt;&lt;isolate_script&gt;true&lt;/isolate_script&gt;&lt;model_id/&gt;&lt;model_table/&gt;&lt;on_load&gt;true&lt;/on_load&gt;&lt;order&gt;100&lt;/order&gt;&lt;reverse_if_false&gt;true&lt;/reverse_if_false&gt;&lt;run_scripts&gt;false&lt;/run_scripts&gt;&lt;script_false&gt;&lt;![CDATA[function onCondition() {

}]]&gt;&lt;/script_false&gt;&lt;script_true&gt;&lt;![CDATA[function onCondition() {

}]]&gt;&lt;/script_true&gt;&lt;set_values/&gt;&lt;short_description&gt;auto populate manager&lt;/short_description&gt;&lt;sys_class_name&gt;sys_ui_policy&lt;/sys_class_name&gt;&lt;sys_created_by&gt;admin&lt;/sys_created_by&gt;&lt;sys_created_on&gt;2025-07-18 12:04:59&lt;/sys_created_on&gt;&lt;sys_domain&gt;global&lt;/sys_domain&gt;&lt;sys_domain_path&gt;/&lt;/sys_domain_path&gt;&lt;sys_id&gt;1dd2aaf1c33a6210a7f1b813e4013118&lt;/sys_id&gt;&lt;sys_mod_count&gt;2&lt;/sys_mod_count&gt;&lt;sys_name&gt;auto populate manager&lt;/sys_name&gt;&lt;sys_overrides/&gt;&lt;sys_package display_value="Leave Management System" source="x_1800027_leve_sys"&gt;9b184465c3beaa10a7f1b813e4013155&lt;/sys_package&gt;&lt;sys_policy/&gt;&lt;sys_scope display_value="Leave Management System"&gt;9b184465c3beaa10a7f1b813e4013155&lt;/sys_scope&gt;&lt;sys_update_name&gt;sys_ui_policy_1dd2aaf1c33a6210a7f1b813e4013118&lt;/sys_update_name&gt;&lt;sys_updated_by&gt;admin&lt;/sys_updated_by&gt;&lt;sys_updated_on&gt;2025-07-18 12:10:59&lt;/sys_updated_on&gt;&lt;table&gt;x_1800027_leve_sys_leave_request&lt;/table&gt;&lt;ui_type&gt;10&lt;/ui_type&gt;&lt;view/&gt;&lt;/sys_ui_policy&gt;&lt;/record_update&gt;</payload>
        <payload_hash>-696054209</payload_hash>
        <record_name>auto populate manager</record_name>
        <reverted_from/>
        <source>687416bdc3b66210a7f1b813e40131fd</source>
        <source_table>sys_update_set</source_table>
        <state>previous</state>
        <sys_created_by>admin</sys_created_by>
        <sys_created_on>2025-07-18 12:10:59</sys_created_on>
        <sys_id>7f84ee75c33a6210a7f1b813e4013102</sys_id>
        <sys_mod_count>0</sys_mod_count>
        <sys_recorded_at>1981d71e2a00000001</sys_recorded_at>
        <sys_updated_by>admin</sys_updated_by>
        <sys_updated_on>2025-07-18 12:10:59</sys_updated_on>
        <type>UI Policy</type>
        <update_guid>7b842675fa3a6210ce37c9d63ceaf59c</update_guid>
        <update_guid_history>7b842675fa3a6210ce37c9d63ceaf59c:-696054209,88142675c83a62102ad681ff3bfccf79:-125164454,84336af14b3a621093094d7cd04f4967:-1245740129</update_guid_history>
    </sys_update_version>
    <sys_metadata_delete action="INSERT_OR_UPDATE">
        <sys_audit_delete/>
        <sys_class_name>sys_metadata_delete</sys_class_name>
        <sys_created_by>admin</sys_created_by>
        <sys_created_on>2025-07-18 12:15:34</sys_created_on>
        <sys_db_object display_value="" name="sys_ui_policy">sys_ui_policy</sys_db_object>
        <sys_id>1339c9cfc4d4479ebc10f0b7212c9a24</sys_id>
        <sys_metadata>1dd2aaf1c33a6210a7f1b813e4013118</sys_metadata>
        <sys_mod_count>0</sys_mod_count>
        <sys_name>auto populate manager</sys_name>
        <sys_package display_value="Leave Management System" source="x_1800027_leve_sys">9b184465c3beaa10a7f1b813e4013155</sys_package>
        <sys_parent display_value="Leave Request">018dd865c332ea10a7f1b813e40131de</sys_parent>
        <sys_policy/>
        <sys_scope display_value="Leave Management System">9b184465c3beaa10a7f1b813e4013155</sys_scope>
        <sys_scope_delete display_value="">1d1e69031d9b45468add883701390559</sys_scope_delete>
        <sys_update_name>sys_ui_policy_1dd2aaf1c33a6210a7f1b813e4013118</sys_update_name>
        <sys_update_version display_value="sys_ui_policy_1dd2aaf1c33a6210a7f1b813e4013118">7f84ee75c33a6210a7f1b813e4013102</sys_update_version>
        <sys_updated_by>admin</sys_updated_by>
        <sys_updated_on>2025-07-18 12:15:34</sys_updated_on>
    </sys_metadata_delete>
</record_update>
